smartsheet_dataframe/__init__.py
smartsheet_dataframe/exceptions.py
smartsheet_dataframe/smartsheet_dataframe.py
smartsheet_dataframe/utils/__init__.py
smartsheet_dataframe/utils/constants.py
smartsheet_dataframe-0.3.7.dist-info/licenses/LICENSE
smartsheet_dataframe-0.3.7.dist-info/METADATA
smartsheet_dataframe-0.3.7.dist-info/WHEEL
smartsheet_dataframe-0.3.7.dist-info/top_level.txt
smartsheet_dataframe-0.3.7.dist-info/RECORD
