Metadata-Version: 2.4
Name: smartsheet-dataframe
Version: 0.3.7
Summary: Converts Smartsheet sheets and reports to a Pandas DataFrame
Author-email: Ridge Coffman <coffman.ridge@gmail.com>
License: MIT
Project-URL: Homepage, https://github.com/RCoff/Smartsheet-DataFrame
Project-URL: Issues, https://github.com/RCoff/Smartsheet-DataFrame/issues
Classifier: Natural Language :: English
Classifier: Programming Language :: Python :: 3
Classifier: Programming Language :: Python :: 3.6
Classifier: Programming Language :: Python :: 3.8
Classifier: Programming Language :: Python :: 3.9
Classifier: Programming Language :: Python :: 3.10
Classifier: Programming Language :: Python :: 3.11
Classifier: Programming Language :: Python :: 3.12
Classifier: License :: OSI Approved :: MIT License
Classifier: Operating System :: OS Independent
Classifier: Topic :: Office/Business :: Financial :: Spreadsheet
Requires-Python: >=3.6.5
License-File: LICENSE
Requires-Dist: pandas>=0.24.0
Requires-Dist: requests>=2.0.0
Dynamic: license-file
